mcp_server_unipile/__init__.py
mcp_server_unipile/server.py
mcp_server_unipile/unipile_client.py
mseep_mcp_server_unipile-0.1.4.dist-info/licenses/LICENSE
mseep_mcp_server_unipile-0.1.4.dist-info/METADATA
mseep_mcp_server_unipile-0.1.4.dist-info/WHEEL
mseep_mcp_server_unipile-0.1.4.dist-info/entry_points.txt
mseep_mcp_server_unipile-0.1.4.dist-info/top_level.txt
mseep_mcp_server_unipile-0.1.4.dist-info/RECORD
