Metadata-Version: 2.4
Name: mseep-mcp-server-unipile
Version: 0.1.4
Summary: A simple unipile MCP server
Author-email: mseep <support@skydeck.ai>
Requires-Python: >=3.11
License-File: LICENSE
Requires-Dist: mcp>=1.0.0
Requires-Dist: python-dotenv>=1.0.0
Requires-Dist: requests>=2.31.0
Requires-Dist: markdownify>=0.13.1
Dynamic: license-file
